mtuprobe/__init__.py
mtuprobe/__main__.py
mtuprobe/ping.py
mtuprobe/probe.py
mtuprobe-0.1.1.dist-info/METADATA
mtuprobe-0.1.1.dist-info/WHEEL
mtuprobe-0.1.1.dist-info/entry_points.txt
mtuprobe-0.1.1.dist-info/RECORD
