Metadata-Version: 2.3
Name: mtuprobe
Version: 0.1.1
Summary: A tool to find out maximum MTU size on an IPv4 path
License: WTFPL
Author: Rémy Sanchez
Author-email: remy.sanchez@hyperthese.net
Requires-Python: >=3.8,<4.0
Classifier: License :: Other/Proprietary License
Classifier: Programming Language :: Python :: 3
Classifier: Programming Language :: Python :: 3.8
Classifier: Programming Language :: Python :: 3.9
Classifier: Programming Language :: Python :: 3.10
Classifier: Programming Language :: Python :: 3.11
Classifier: Programming Language :: Python :: 3.12
Classifier: Programming Language :: Python :: 3.13
Project-URL: Documentation, https://github.com/Xowap/mtuprobe
Project-URL: Homepage, https://github.com/Xowap/mtuprobe
Project-URL: Repository, https://github.com/Xowap/mtuprobe
